MANIFEST.in
ez_setup.py
setup.cfg
setup.py
buildutils/__init__.py
buildutils/cmd.py
buildutils/editor.py
buildutils/pycount.py
buildutils/pysetup.py
buildutils.egg-info/PKG-INFO
buildutils.egg-info/SOURCES.txt
buildutils.egg-info/dependency_links.txt
buildutils.egg-info/entry_points.txt
buildutils.egg-info/top_level.txt
buildutils/announce_command/__init__.py
buildutils/announce_command/announce.py
buildutils/command/__init__.py
buildutils/command/addcommand.py
buildutils/command/bundle.py
buildutils/command/checksum.py
buildutils/command/customcommand.py
buildutils/command/etags.py
buildutils/command/flakes.py
buildutils/command/info.py
buildutils/command/stats.py
buildutils/command/svntag.py
buildutils/compat/__init__.py
buildutils/compat/string_template.py
buildutils/publish_command/__init__.py
buildutils/publish_command/publish.py
buildutils/pudge_command/__init__.py
buildutils/pudge_command/pudge.py
buildutils/pytest_command/__init__.py
buildutils/pytest_command/pytest.py
buildutils/test/__init__.py
buildutils/test/test_compat.py
buildutils/test/test_publish.py
doc/TODO.rst
doc/commands.rst
doc/extensions.rst
doc/guide.rst
doc/index.rst
doc/commands/announce.rst
doc/commands/checksum.rst
doc/commands/etags.rst
doc/commands/flakes.rst
doc/commands/info.rst
doc/commands/publish.rst
doc/commands/pudge.rst
doc/commands/pytest.rst
doc/commands/stats.rst
doc/commands/svntag.rst
