Metadata-Version: 1.0
Name: buildutils
Version: 0.3
Summary: Distutils extensions for developing Python libraries and applications.
Home-page: UNKNOWN
Author: Ian Bicking, Ryan Tomayko
Author-email: ianb@colorstudy.com
License: MIT
Keywords: distutils development make build
Platform: UNKNOWN
Classifier: Development Status :: 4 - Beta
Classifier: Environment :: Console
Classifier: Intended Audience :: Developers
Classifier: Intended Audience :: System Administrators
Classifier: License :: OSI Approved :: MIT License
Classifier: Operating System :: OS Independent
Classifier: Programming Language :: Python
Classifier: Topic :: Software Development :: Build Tools
Classifier: Topic :: System :: Installation/Setup
Classifier: Topic :: System :: Software Distribution
Classifier: Topic :: Utilities
